./.gitignore
./1136_process.log
./LICENSE
./PKG-INFO
./README.md
./gitlab.py
./language.json
./package_name
./pyproject.toml
./.claude-plugin/marketplace.json
./plugins/gitlab-mr-review/.mcp.json
./plugins/gitlab-mr-review/start.sh
./plugins/gitlab-mr-review/.claude-plugin/plugin.json
./plugins/gitlab-mr-review/commands/review-gitlab-mr.md
./plugins/gitlab-mr-review/examples/claude_desktop_config.json
./plugins/gitlab-mr-review/server/gitlab.py
./plugins/gitlab-mr-review/server/pyproject.toml
iflow_mcp_hosseinsafari_gitlab_mr_mcp-0.1.0.dist-info/METADATA
iflow_mcp_hosseinsafari_gitlab_mr_mcp-0.1.0.dist-info/WHEEL
iflow_mcp_hosseinsafari_gitlab_mr_mcp-0.1.0.dist-info/entry_points.txt
iflow_mcp_hosseinsafari_gitlab_mr_mcp-0.1.0.dist-info/licenses/LICENSE
iflow_mcp_hosseinsafari_gitlab_mr_mcp-0.1.0.dist-info/RECORD
