Metadata-Version: 2.4
Name: iflow-mcp_hosseinsafari_gitlab-mr-mcp
Version: 0.1.0
License-File: LICENSE
Requires-Dist: httpx
Requires-Dist: mcp
